{
	"name": "endNextLevelButton",
	"plugin-id": "Sprite",
	"sid": 441469598940367,
	"isGlobal": false,
	"instanceVariables": [],
	"behaviorTypes": [],
	"effectTypes": [],
	"animations": {
		"items": [
			{
				"frames": [
					{
						"width": 114,
						"height": 45,
						"originX": 0.5,
						"originY": 0.5,
						"originalSource": "",
						"exportFormat": "lossless",
						"exportQuality": 0.8,
						"imageSpriteId": 4361604,
						"collisionPoly": {
							"points": [
								0.043859649122807015,
								0.044444444444444446,
								0.956140350877193,
								0.044444444444444446,
								0.9824561403508771,
								0.1111111111111111,
								0.9912280701754386,
								0.15555555555555556,
								0.9912280701754386,
								0.8666666666666667,
								0.9824561403508771,
								0.9111111111111111,
								0.9473684210526315,
								0.9777777777777777,
								0.03508771929824561,
								0.9555555555555556,
								0.017543859649122806,
								0.9111111111111111,
								0.008771929824561403,
								0.8666666666666667,
								0.008771929824561403,
								0.13333333333333333
							]
						},
						"useCollisionPoly": true,
						"duration": 1,
						"tag": ""
					}
				],
				"sid": 294985672493726,
				"name": "Animation 1",
				"isLooping": false,
				"isPingPong": false,
				"repeatCount": 1,
				"repeatTo": 0,
				"speed": 5
			}
		],
		"subfolders": []
	}
}